{
    "dataset": "DuIE",
    "model": "multi_head_selection",
    "data_root": "data/DuIE/multi_head_selection",
    "raw_data_root": "raw_data/DuIE",
    "train": "train_data.json",
    "dev": "dev_data.json",
    "relation_vocab": "relation_vocab.json",
    "print_epoch": 1,
    "evaluation_epoch":49,
    "max_text_len": 100,
    "cell_name": "lstm",
    "emb_size": 300,
    "rel_emb_size": 100,
    "bio_emb_size": 50,
    "hidden_size": 300,
    "threshold": 0.5,
    "activation": "tanh",
    "optimizer": "adam",
    "epoch_num": 50,
    "train_batch": 150,
    "eval_batch": 150,
    "gpu":1,
    "use_gcn":0,
    "use_multi_gpu":0
}